<?xml version="1.0"?>
<!DOCTYPE hibernate-mapping PUBLIC "-//Hibernate/Hibernate Mapping DTD 3.0/EN"
"http://hibernate.sourceforge.net/hibernate-mapping-3.0.dtd">

<hibernate-mapping>

<class name="Vo.CountryVo" table="country">

	<id name="cid" column="Id">
	<generator class="increment" />
	</id>
	<property name="countryName">
	<column name="CountryName"/>
	</property> 
	<property name="CountryDescription">
	<column name="CountryDesc"/>
	</property>

</class>

</hibernate-mapping>